.DS_Store
docker_registry_driver_git-0.9.001-py2.7-nspkg.pth
docker_registry/.DS_Store
docker_registry/drivers/gitdriver.py
docker_registry_driver_git-0.9.001.dist-info/DESCRIPTION.rst
docker_registry_driver_git-0.9.001.dist-info/METADATA
docker_registry_driver_git-0.9.001.dist-info/metadata.json
docker_registry_driver_git-0.9.001.dist-info/namespace_packages.txt
docker_registry_driver_git-0.9.001.dist-info/pbr.json
docker_registry_driver_git-0.9.001.dist-info/RECORD
docker_registry_driver_git-0.9.001.dist-info/top_level.txt
docker_registry_driver_git-0.9.001.dist-info/WHEEL
docker_registry_driver_git-0.9.001.dist-info/zip-safe
