Metadata-Version: 2.0
Name: docker-registry-driver-git
Version: 0.9.001
Summary: Docker registry backend git driver
Home-page: https://github.com/pyotr777/docker-registry-driver-git
Author: Peter Bryzgalov
Author-email: peterbryz@yahoo.com
License: Copyright 2015 RIKEN AICS
Requires-Dist: docker-registry-core (>=2,<3)
Requires-Dist: GitPython (>=0.3)
